mgait/CAD/__init__.py
mgait/CAD/base_cad.py
mgait/CAD/cad.py
mgait/CAD/utils/__init__.py
mgait/CAD/utils/cad_utils.py
mgait/GSD/GSD1.py
mgait/GSD/GSD2.py
mgait/GSD/GSD3.py
mgait/GSD/GSD4.py
mgait/GSD/GSD5.py
mgait/GSD/__init__.py
mgait/GSD/base_gsd.py
mgait/GSD/utils/ActivityCounts.py
mgait/GSD/utils/GSD1_utils.py
mgait/GSD/utils/GSD3_utils.py
mgait/GSD/utils/__init__.py
mgait/GSD/utils/cart_to_spher.py
mgait/GSD/utils/cwb.py
mgait/GSD/utils/gravity_remove_butter.py
mgait/GSD/utils/merge_bouts.py
mgait/ICD/ICD1.py
mgait/ICD/ICD2.py
mgait/ICD/ICD3.py
mgait/ICD/ICD4.py
mgait/ICD/ICD5.py
mgait/ICD/ICD6.py
mgait/ICD/__init__.py
mgait/ICD/base_ic.py
mgait/ICD/utils/__init__.py
mgait/ICD/utils/auto_cov_unbiased.py
mgait/ICD/utils/dominant_frequency.py
mgait/ICD/utils/dtwDasGupta.py
mgait/ICD/utils/find_maxima.py
mgait/ICD/utils/find_minima.py
mgait/ICD/utils/peakfind.py
mgait/ICD/utils/zero_crossings.py
mgait/SL/SL1.py
mgait/SL/SL2.py
mgait/SL/SL3.py
mgait/SL/__init__.py
mgait/SL/base_sl.py
mgait/SL/utils/SL_utils.py
mgait/SL/utils/__init__.py
mgait/WS/__init__.py
mgait/WS/base_ws.py
mgait/WS/walking_speed.py
mgait/__init__.py
mgait/aggregation/__init__.py
mgait/aggregation/_aggregator_base.py
mgait/aggregation/_generic_aggregator.py
mgait/aggregation/_lab_aggregator.py
mgait/data/__init__.py
mgait/data/base_data.py
mgait/data_loader/__init__.py
mgait/data_loader/cwa_data_loader.py
mgait/interpolation_ts/__init__.py
mgait/interpolation_ts/interpolation.py
mgait/pipeline/__init__.py
mgait/pipeline/iterator.py
mgait/pipeline/multimobility_pipeline.py
mgait/pipeline/pipeline_base.py
mgait/pipeline/utils/__init__.py
mgait/pipeline/utils/_operations.py
mgait/pipeline/utils/_stride_filtering.py
mgait/pipeline/utils/_thresholds.py
mgait/pipeline/utils/_var_dmos.py
mgait/pipeline/utils/_wb_assembly.py
mgait/pipeline/utils/_wb_criteria.py
mgait/pipeline/utils/alpha.py
mgait/pipeline/utils/datapoint_check.py
mgait/pipeline/utils/dmo_thresholds.csv
mgait-0.1.0.dist-info/METADATA
mgait-0.1.0.dist-info/WHEEL
mgait-0.1.0.dist-info/licenses/LICENSE
mgait-0.1.0.dist-info/RECORD
